redis_director/__init__.py
redis_director/callback.py
redis_director/constants.py
redis_director/handler.py
redis_director/publisher.py
redis_director/subscriber.py
redis_director-0.7.8.dist-info/METADATA
redis_director-0.7.8.dist-info/WHEEL
redis_director-0.7.8.dist-info/RECORD
